Classfile /Users/someshbalani/workspace/j--/ExceptionHandlers.class
  Last modified 26-Apr-2023; size 1214 bytes
  SHA-256 checksum 4abfb8a7b63ab768b69b68ed168b9077ad7846528b4b67b9635e6ac5c8a51c77
  Compiled from "ExceptionHandlers.java"
public class ExceptionHandlers
  minor version: 0
  major version: 62
  flags: (0x0021) ACC_PUBLIC, ACC_SUPER
  this_class: #14                         // ExceptionHandlers
  super_class: #2                         // java/lang/Object
  interfaces: 0, fields: 0, methods: 3, attributes: 1
Constant pool:
   #1 = Methodref          #2.#3          // java/lang/Object."<init>":()V
   #2 = Class              #4             // java/lang/Object
   #3 = NameAndType        #5:#6          // "<init>":()V
   #4 = Utf8               java/lang/Object
   #5 = Utf8               <init>
   #6 = Utf8               ()V
   #7 = Methodref          #8.#9          // java/lang/Double.parseDouble:(Ljava/lang/String;)D
   #8 = Class              #10            // java/lang/Double
   #9 = NameAndType        #11:#12        // parseDouble:(Ljava/lang/String;)D
  #10 = Utf8               java/lang/Double
  #11 = Utf8               parseDouble
  #12 = Utf8               (Ljava/lang/String;)D
  #13 = Methodref          #14.#15        // ExceptionHandlers.sqrt:(D)D
  #14 = Class              #16            // ExceptionHandlers
  #15 = NameAndType        #17:#18        // sqrt:(D)D
  #16 = Utf8               ExceptionHandlers
  #17 = Utf8               sqrt
  #18 = Utf8               (D)D
  #19 = Fieldref           #20.#21        // java/lang/System.out:Ljava/io/PrintStream;
  #20 = Class              #22            // java/lang/System
  #21 = NameAndType        #23:#24        // out:Ljava/io/PrintStream;
  #22 = Utf8               java/lang/System
  #23 = Utf8               out
  #24 = Utf8               Ljava/io/PrintStream;
  #25 = Methodref          #26.#27        // java/io/PrintStream.println:(D)V
  #26 = Class              #28            // java/io/PrintStream
  #27 = NameAndType        #29:#30        // println:(D)V
  #28 = Utf8               java/io/PrintStream
  #29 = Utf8               println
  #30 = Utf8               (D)V
  #31 = String             #32            // Done!
  #32 = Utf8               Done!
  #33 = Methodref          #26.#34        // java/io/PrintStream.println:(Ljava/lang/String;)V
  #34 = NameAndType        #29:#35        // println:(Ljava/lang/String;)V
  #35 = Utf8               (Ljava/lang/String;)V
  #36 = Class              #37            // java/lang/ArrayIndexOutOfBoundsException
  #37 = Utf8               java/lang/ArrayIndexOutOfBoundsException
  #38 = String             #39            // x not specified
  #39 = Utf8               x not specified
  #40 = Class              #41            // java/lang/NumberFormatException
  #41 = Utf8               java/lang/NumberFormatException
  #42 = String             #43            // x must be a double
  #43 = Utf8               x must be a double
  #44 = Class              #45            // java/lang/IllegalArgumentException
  #45 = Utf8               java/lang/IllegalArgumentException
  #46 = Methodref          #44.#47        // java/lang/IllegalArgumentException.getMessage:()Ljava/lang/String;
  #47 = NameAndType        #48:#49        // getMessage:()Ljava/lang/String;
  #48 = Utf8               getMessage
  #49 = Utf8               ()Ljava/lang/String;
  #50 = String             #51            // x must be positve
  #51 = Utf8               x must be positve
  #52 = Methodref          #44.#53        // java/lang/IllegalArgumentException."<init>":(Ljava/lang/String;)V
  #53 = NameAndType        #5:#35         // "<init>":(Ljava/lang/String;)V
  #54 = Methodref          #55.#15        // java/lang/Math.sqrt:(D)D
  #55 = Class              #56            // java/lang/Math
  #56 = Utf8               java/lang/Math
  #57 = Utf8               Code
  #58 = Utf8               LineNumberTable
  #59 = Utf8               main
  #60 = Utf8               ([Ljava/lang/String;)V
  #61 = Utf8               StackMapTable
  #62 = Class              #63            // java/lang/Throwable
  #63 = Utf8               java/lang/Throwable
  #64 = Utf8               Exceptions
  #65 = Utf8               SourceFile
  #66 = Utf8               ExceptionHandlers.java
{
  public ExceptionHandlers();
    descriptor: ()V
    flags: (0x0001) ACC_PUBLIC
    Code:
      stack=1, locals=1, args_size=1
         0: aload_0
         1: invokespecial #1                  // Method java/lang/Object."<init>":()V
         4: return
      LineNumberTable:
        line 9: 0

  public static void main(java.lang.String[]);
    descriptor: ([Ljava/lang/String;)V
    flags: (0x0009) ACC_PUBLIC, ACC_STATIC
    Code:
      stack=3, locals=6, args_size=1
         0: aload_0
         1: iconst_0
         2: aaload
         3: invokestatic  #7                  // Method java/lang/Double.parseDouble:(Ljava/lang/String;)D
         6: dstore_1
         7: dload_1
         8: invokestatic  #13                 // Method sqrt:(D)D
        11: dstore_3
        12: getstatic     #19                 // Field java/lang/System.out:Ljava/io/PrintStream;
        15: dload_3
        16: invokevirtual #25                 // Method java/io/PrintStream.println:(D)V
        19: getstatic     #19                 // Field java/lang/System.out:Ljava/io/PrintStream;
        22: ldc           #31                 // String Done!
        24: invokevirtual #33                 // Method java/io/PrintStream.println:(Ljava/lang/String;)V
        27: goto          105
        30: astore_1
        31: getstatic     #19                 // Field java/lang/System.out:Ljava/io/PrintStream;
        34: ldc           #38                 // String x not specified
        36: invokevirtual #33                 // Method java/io/PrintStream.println:(Ljava/lang/String;)V
        39: getstatic     #19                 // Field java/lang/System.out:Ljava/io/PrintStream;
        42: ldc           #31                 // String Done!
        44: invokevirtual #33                 // Method java/io/PrintStream.println:(Ljava/lang/String;)V
        47: goto          105
        50: astore_1
        51: getstatic     #19                 // Field java/lang/System.out:Ljava/io/PrintStream;
        54: ldc           #42                 // String x must be a double
        56: invokevirtual #33                 // Method java/io/PrintStream.println:(Ljava/lang/String;)V
        59: getstatic     #19                 // Field java/lang/System.out:Ljava/io/PrintStream;
        62: ldc           #31                 // String Done!
        64: invokevirtual #33                 // Method java/io/PrintStream.println:(Ljava/lang/String;)V
        67: goto          105
        70: astore_1
        71: getstatic     #19                 // Field java/lang/System.out:Ljava/io/PrintStream;
        74: aload_1
        75: invokevirtual #46                 // Method java/lang/IllegalArgumentException.getMessage:()Ljava/lang/String;
        78: invokevirtual #33                 // Method java/io/PrintStream.println:(Ljava/lang/String;)V
        81: getstatic     #19                 // Field java/lang/System.out:Ljava/io/PrintStream;
        84: ldc           #31                 // String Done!
        86: invokevirtual #33                 // Method java/io/PrintStream.println:(Ljava/lang/String;)V
        89: goto          105
        92: astore        5
        94: getstatic     #19                 // Field java/lang/System.out:Ljava/io/PrintStream;
        97: ldc           #31                 // String Done!
        99: invokevirtual #33                 // Method java/io/PrintStream.println:(Ljava/lang/String;)V
       102: aload         5
       104: athrow
       105: return
      Exception table:
         from    to  target type
             0    19    30   Class java/lang/ArrayIndexOutOfBoundsException
             0    19    50   Class java/lang/NumberFormatException
             0    19    70   Class java/lang/IllegalArgumentException
             0    19    92   any
            30    39    92   any
            50    59    92   any
            70    81    92   any
            92    94    92   any
      LineNumberTable:
        line 12: 0
        line 13: 7
        line 14: 12
        line 22: 19
        line 23: 27
        line 15: 30
        line 16: 31
        line 22: 39
        line 23: 47
        line 17: 50
        line 18: 51
        line 22: 59
        line 23: 67
        line 19: 70
        line 20: 71
        line 22: 81
        line 23: 89
        line 22: 92
        line 23: 102
        line 24: 105
      StackMapTable: number_of_entries = 5
        frame_type = 94 /* same_locals_1_stack_item */
          stack = [ class java/lang/ArrayIndexOutOfBoundsException ]
        frame_type = 83 /* same_locals_1_stack_item */
          stack = [ class java/lang/NumberFormatException ]
        frame_type = 83 /* same_locals_1_stack_item */
          stack = [ class java/lang/IllegalArgumentException ]
        frame_type = 85 /* same_locals_1_stack_item */
          stack = [ class java/lang/Throwable ]
        frame_type = 12 /* same */

  private static double sqrt(double) throws java.lang.IllegalArgumentException;
    descriptor: (D)D
    flags: (0x000a) ACC_PRIVATE, ACC_STATIC
    Code:
      stack=4, locals=2, args_size=1
         0: dload_0
         1: dconst_0
         2: dcmpg
         3: ifge          16
         6: new           #44                 // class java/lang/IllegalArgumentException
         9: dup
        10: ldc           #50                 // String x must be positve
        12: invokespecial #52                 // Method java/lang/IllegalArgumentException."<init>":(Ljava/lang/String;)V
        15: athrow
        16: dload_0
        17: invokestatic  #54                 // Method java/lang/Math.sqrt:(D)D
        20: dreturn
      LineNumberTable:
        line 27: 0
        line 28: 6
        line 30: 16
      StackMapTable: number_of_entries = 1
        frame_type = 16 /* same */
    Exceptions:
      throws java.lang.IllegalArgumentException
}
SourceFile: "ExceptionHandlers.java"
