Classfile /Users/someshbalani/workspace/j--/SwitchStatement.class
  Last modified 23-Apr-2023; size 1449 bytes
  SHA-256 checksum df5e3e0f560b4c7513946e6f6d00e29d5a36f7b5b245d476cbbad5a75423a9f3
  Compiled from "SwitchStatement.java"
public class SwitchStatement
  minor version: 0
  major version: 62
  flags: (0x0021) ACC_PUBLIC, ACC_SUPER
  this_class: #54                         // SwitchStatement
  super_class: #2                         // java/lang/Object
  interfaces: 0, fields: 0, methods: 2, attributes: 3
Constant pool:
   #1 = Methodref          #2.#3          // java/lang/Object."<init>":()V
   #2 = Class              #4             // java/lang/Object
   #3 = NameAndType        #5:#6          // "<init>":()V
   #4 = Utf8               java/lang/Object
   #5 = Utf8               <init>
   #6 = Utf8               ()V
   #7 = Class              #8             // java/util/Random
   #8 = Utf8               java/util/Random
   #9 = Methodref          #7.#3          // java/util/Random."<init>":()V
  #10 = Methodref          #7.#11         // java/util/Random.nextInt:(I)I
  #11 = NameAndType        #12:#13        // nextInt:(I)I
  #12 = Utf8               nextInt
  #13 = Utf8               (I)I
  #14 = String             #15            //
  #15 = Utf8
  #16 = String             #17            // Ace
  #17 = Utf8               Ace
  #18 = String             #19            // Jack
  #19 = Utf8               Jack
  #20 = String             #21            // Queen
  #21 = Utf8               Queen
  #22 = String             #23            // King
  #23 = Utf8               King
  #24 = Methodref          #25.#26        // java/lang/String.valueOf:(I)Ljava/lang/String;
  #25 = Class              #27            // java/lang/String
  #26 = NameAndType        #28:#29        // valueOf:(I)Ljava/lang/String;
  #27 = Utf8               java/lang/String
  #28 = Utf8               valueOf
  #29 = Utf8               (I)Ljava/lang/String;
  #30 = String             #31            // Spades
  #31 = Utf8               Spades
  #32 = String             #33            // Hearts
  #33 = Utf8               Hearts
  #34 = String             #35            // Diamonds
  #35 = Utf8               Diamonds
  #36 = String             #37            // Clubs
  #37 = Utf8               Clubs
  #38 = Fieldref           #39.#40        // java/lang/System.out:Ljava/io/PrintStream;
  #39 = Class              #41            // java/lang/System
  #40 = NameAndType        #42:#43        // out:Ljava/io/PrintStream;
  #41 = Utf8               java/lang/System
  #42 = Utf8               out
  #43 = Utf8               Ljava/io/PrintStream;
  #44 = InvokeDynamic      #0:#45         // #0:makeConcatWithConstants:(Ljava/lang/String;Ljava/lang/String;)Ljava/lang/String;
  #45 = NameAndType        #46:#47        // makeConcatWithConstants:(Ljava/lang/String;Ljava/lang/String;)Ljava/lang/String;
  #46 = Utf8               makeConcatWithConstants
  #47 = Utf8               (Ljava/lang/String;Ljava/lang/String;)Ljava/lang/String;
  #48 = Methodref          #49.#50        // java/io/PrintStream.println:(Ljava/lang/String;)V
  #49 = Class              #51            // java/io/PrintStream
  #50 = NameAndType        #52:#53        // println:(Ljava/lang/String;)V
  #51 = Utf8               java/io/PrintStream
  #52 = Utf8               println
  #53 = Utf8               (Ljava/lang/String;)V
  #54 = Class              #55            // SwitchStatement
  #55 = Utf8               SwitchStatement
  #56 = Utf8               Code
  #57 = Utf8               LineNumberTable
  #58 = Utf8               main
  #59 = Utf8               ([Ljava/lang/String;)V
  #60 = Utf8               StackMapTable
  #61 = Class              #62            // "[Ljava/lang/String;"
  #62 = Utf8               [Ljava/lang/String;
  #63 = Utf8               SourceFile
  #64 = Utf8               SwitchStatement.java
  #65 = Utf8               BootstrapMethods
  #66 = MethodHandle       6:#67          // REF_invokeStatic java/lang/invoke/StringConcatFactory.makeConcatWithConstants:(Ljava/lang/invoke/MethodHandles$Lookup;Ljava/lang/String;Ljava/lang/invoke/MethodType;Ljava/lang/String;[Ljava/lang/Object;)Ljava/lang/invoke/CallSite;
  #67 = Methodref          #68.#69        // java/lang/invoke/StringConcatFactory.makeConcatWithConstants:(Ljava/lang/invoke/MethodHandles$Lookup;Ljava/lang/String;Ljava/lang/invoke/MethodType;Ljava/lang/String;[Ljava/lang/Object;)Ljava/lang/invoke/CallSite;
  #68 = Class              #70            // java/lang/invoke/StringConcatFactory
  #69 = NameAndType        #46:#71        // makeConcatWithConstants:(Ljava/lang/invoke/MethodHandles$Lookup;Ljava/lang/String;Ljava/lang/invoke/MethodType;Ljava/lang/String;[Ljava/lang/Object;)Ljava/lang/invoke/CallSite;
  #70 = Utf8               java/lang/invoke/StringConcatFactory
  #71 = Utf8               (Ljava/lang/invoke/MethodHandles$Lookup;Ljava/lang/String;Ljava/lang/invoke/MethodType;Ljava/lang/String;[Ljava/lang/Object;)Ljava/lang/invoke/CallSite;
  #72 = String             #73            // \u0001 of \u0001
  #73 = Utf8               \u0001 of \u0001
  #74 = Utf8               InnerClasses
  #75 = Class              #76            // java/lang/invoke/MethodHandles$Lookup
  #76 = Utf8               java/lang/invoke/MethodHandles$Lookup
  #77 = Class              #78            // java/lang/invoke/MethodHandles
  #78 = Utf8               java/lang/invoke/MethodHandles
  #79 = Utf8               Lookup
{
  public SwitchStatement();
    descriptor: ()V
    flags: (0x0001) ACC_PUBLIC
    Code:
      stack=1, locals=1, args_size=1
         0: aload_0
         1: invokespecial #1                  // Method java/lang/Object."<init>":()V
         4: return
      LineNumberTable:
        line 5: 0

  public static void main(java.lang.String[]);
    descriptor: ([Ljava/lang/String;)V
    flags: (0x0009) ACC_PUBLIC, ACC_STATIC
    Code:
      stack=3, locals=6, args_size=1
         0: new           #7                  // class java/util/Random
         3: dup
         4: invokespecial #9                  // Method java/util/Random."<init>":()V
         7: astore_1
         8: aload_1
         9: bipush        13
        11: invokevirtual #10                 // Method java/util/Random.nextInt:(I)I
        14: iconst_1
        15: iadd
        16: istore_2
        17: aload_1
        18: iconst_3
        19: invokevirtual #10                 // Method java/util/Random.nextInt:(I)I
        22: iconst_1
        23: iadd
        24: istore_3
        25: ldc           #14                 // String
        27: astore        4
        29: iload_2
        30: lookupswitch  { // 4
                       1: 72
                      11: 79
                      12: 86
                      13: 93
                 default: 100
            }
        72: ldc           #16                 // String Ace
        74: astore        4
        76: goto          106
        79: ldc           #18                 // String Jack
        81: astore        4
        83: goto          106
        86: ldc           #20                 // String Queen
        88: astore        4
        90: goto          106
        93: ldc           #22                 // String King
        95: astore        4
        97: goto          106
       100: iload_2
       101: invokestatic  #24                 // Method java/lang/String.valueOf:(I)Ljava/lang/String;
       104: astore        4
       106: ldc           #14                 // String
       108: astore        5
       110: iload_3
       111: tableswitch   { // 1 to 4
                       1: 140
                       2: 147
                       3: 154
                       4: 161
                 default: 165
            }
       140: ldc           #30                 // String Spades
       142: astore        5
       144: goto          165
       147: ldc           #32                 // String Hearts
       149: astore        5
       151: goto          165
       154: ldc           #34                 // String Diamonds
       156: astore        5
       158: goto          165
       161: ldc           #36                 // String Clubs
       163: astore        5
       165: getstatic     #38                 // Field java/lang/System.out:Ljava/io/PrintStream;
       168: aload         4
       170: aload         5
       172: invokedynamic #44,  0             // InvokeDynamic #0:makeConcatWithConstants:(Ljava/lang/String;Ljava/lang/String;)Ljava/lang/String;
       177: invokevirtual #48                 // Method java/io/PrintStream.println:(Ljava/lang/String;)V
       180: return
      LineNumberTable:
        line 7: 0
        line 8: 8
        line 9: 17
        line 10: 25
        line 11: 29
        line 13: 72
        line 14: 76
        line 16: 79
        line 17: 83
        line 19: 86
        line 20: 90
        line 22: 93
        line 23: 97
        line 25: 100
        line 27: 106
        line 28: 110
        line 30: 140
        line 31: 144
        line 33: 147
        line 34: 151
        line 36: 154
        line 37: 158
        line 39: 161
        line 42: 165
        line 43: 180
      StackMapTable: number_of_entries = 11
        frame_type = 255 /* full_frame */
          offset_delta = 72
          locals = [ class "[Ljava/lang/String;", class java/util/Random, int, int, class java/lang/String ]
          stack = []
        frame_type = 6 /* same */
        frame_type = 6 /* same */
        frame_type = 6 /* same */
        frame_type = 6 /* same */
        frame_type = 5 /* same */
        frame_type = 252 /* append */
          offset_delta = 33
          locals = [ class java/lang/String ]
        frame_type = 6 /* same */
        frame_type = 6 /* same */
        frame_type = 6 /* same */
        frame_type = 3 /* same */
}
SourceFile: "SwitchStatement.java"
BootstrapMethods:
  0: #66 REF_invokeStatic java/lang/invoke/StringConcatFactory.makeConcatWithConstants:(Ljava/lang/invoke/MethodHandles$Lookup;Ljava/lang/String;Ljava/lang/invoke/MethodType;Ljava/lang/String;[Ljava/lang/Object;)Ljava/lang/invoke/CallSite;
    Method arguments:
      #72 \u0001 of \u0001
InnerClasses:
  public static final #79= #75 of #77;    // Lookup=class java/lang/invoke/MethodHandles$Lookup of class java/lang/invoke/MethodHandles
